parseur/__init__.py
parseur/cli.py
parseur/client.py
parseur/config.py
parseur/decorator.py
parseur/document.py
parseur/event.py
parseur/mailbox.py
parseur/server.py
parseur/utils.py
parseur/webhook.py
parseur/schemas/__init__.py
parseur/schemas/document.py
parseur/schemas/mailbox.py
parseur/schemas/paserfield.py
parseur/schemas/webhook.py
parseur_py-1.5.0.dist-info/licenses/LICENSE
parseur_py-1.5.0.dist-info/METADATA
parseur_py-1.5.0.dist-info/WHEEL
parseur_py-1.5.0.dist-info/entry_points.txt
parseur_py-1.5.0.dist-info/top_level.txt
parseur_py-1.5.0.dist-info/RECORD
