Metadata-Version: 2.4
Name: parseur-py
Version: 1.5.0
Summary: A Python client for the Parseur.com API to manage mailboxes, documents, uploads, and listen for new parsing events.
Author-email: Parseur Team <admin@parseur.com>
Project-URL: Homepage, https://github.com/parseur/parseur-py
Project-URL: Repository, https://github.com/parseur/parseur-py
Project-URL: Issues, https://github.com/parseur/parseur-py/issues
Requires-Python: >=3.8
License-File: LICENSE
Requires-Dist: click>=8.2.1
Requires-Dist: requests>=2.31.0
Requires-Dist: marshmallow>=4.0.0
Provides-Extra: listener
Requires-Dist: Flask>=3.1.0; extra == "listener"
Dynamic: license-file
